MANIFEST.in
README.md
recrypto_build.py
setup.py
bin/genkey.py
cppsrc/crypto.cpp
cppsrc/recrypto.h
cppsrc/redeclipse-license.txt
cppsrc/tools.cpp
cppsrc/tools.h
recrypto/__init__.py
recrypto.egg-info/PKG-INFO
recrypto.egg-info/SOURCES.txt
recrypto.egg-info/dependency_links.txt
recrypto.egg-info/requires.txt
recrypto.egg-info/top_level.txt