Metadata-Version: 1.0
Name: recrypto
Version: 0.0.1
Summary: Python module for Red Eclipse cryptography
Home-page: UNKNOWN
Author: zaquest
Author-email: UNKNOWN
License: zlib
Platform: UNKNOWN
